LICENSE
README.txt
setup.cfg
setup.py
TracAdsPanel.egg-info/PKG-INFO
TracAdsPanel.egg-info/SOURCES.txt
TracAdsPanel.egg-info/dependency_links.txt
TracAdsPanel.egg-info/entry_points.txt
TracAdsPanel.egg-info/top_level.txt
adspanel/__init__.py
adspanel/admin.py
adspanel/config.py
adspanel/web_ui.py
adspanel/templates/ads_admin.html
