Metadata-Version: 1.0
Name: TracAdsPanel
Version: 0.1.1
Summary: Trac plugin designed to display ads on your Trac environment
Home-page: UNKNOWN
Author: Pedro Algarvio
Author-email: ufs@ufsoft.org
License: UNKNOWN
Platform: UNKNOWN
